Metadata-Version: 2.1
Name: django-fancy-cronfield-alt
Version: 1.0.1
Summary: A nice and customizable cronfield
Home-page: https://github.com/rsiemens/django-fancy-cronfield
Author: Saeed Salehian
Author-email: saeed.sq@gmail.com
Maintainer: Ryan Siemens
Maintainer-email: ryanjsiemens@gmail.com
License: BSD License
Platform: OS Independent
Classifier: Development Status :: 5 - Production/Stable
Classifier: Environment :: Web Environment
Classifier: Framework :: Django
Classifier: Intended Audience :: Developers
Classifier: License :: OSI Approved :: BSD License
Classifier: Operating System :: OS Independent
Classifier: Programming Language :: Python
Classifier: Topic :: Internet :: WWW/HTTP :: Dynamic Content
Classifier: Topic :: Software Development
Classifier: Topic :: Software Development :: Libraries :: Application Frameworks
Classifier: Programming Language :: Python
Classifier: Programming Language :: Python :: 3 :: Only
Classifier: Programming Language :: Python :: 3
Classifier: Programming Language :: Python :: 3.6
Classifier: Programming Language :: Python :: 3.7
Classifier: Programming Language :: Python :: 3.8
Classifier: Framework :: Django
Classifier: Framework :: Django :: 1.11
Classifier: Framework :: Django :: 2.0
Classifier: Framework :: Django :: 2.1
Classifier: Framework :: Django :: 2.2
Requires-Dist: django (<3.0,>=1.11)
Requires-Dist: python-crontab (==1.9.5)
